{
  "protocol_version" : "0.0.6",
  "configuration" : {
    "version" : "(6.13.0) (explicit/4516165c149)",
    "tlc" : "__thread",
    "sigsgev" : "normal",
    "notifications" : "kqueue",
    "architecture" : "arm64",
    "disabled_features" : "com,shared_perfcounters",
    "smallconfig" : "disabled",
    "bigarrays" : "disabled",
    "softdebug" : "enabled",
    "interpreter" : "enabled",
    "llvm_support" : "disabled",
    "suspend" : "preemptive"
  },
  "memory" : {
    "Resident Size" : "454885376",
    "Virtual Size" : "424728182784",
    "minor_gc_time" : "0",
    "major_gc_time" : "1854073",
    "minor_gc_count" : "0",
    "major_gc_count" : "22",
    "major_gc_time_concurrent" : "0"
 },
  "threads" : [
 {
    "is_managed" : false,
    "offset_free_hash" : "0x0",
    "offset_rich_hash" : "0x0",
    "crashed" : false,
    "native_thread_id" : "0x3151f7000",
    "thread_info_addr" : "0x12d8d9a00",
    "thread_name" : "Debugger agent",
    "ctx" : {
      "IP" : "0x189aad6d4",
      "SP" : "0x3151f6aa0",
      "BP" : "0x3151f6ae0"
  },
    "unmanaged_frames" : [
  {
      "is_managed" : "false",
      "native_address" : "0x3147c1c58",
      "native_offset" : "0x00000"
   }
,
  {
      "is_managed" : "false",
      "native_address" : "0x3148f8788",
      "native_offset" : "0x00000"
   }
,
  {
      "is_managed" : "false",
      "native_address" : "0x3148f8ae4",
      "native_offset" : "0x00000"
   }
,
  {
      "is_managed" : "false",
      "native_address" : "0x3148f88ac",
      "native_offset" : "0x00000"
   }
,
  {
      "is_managed" : "false",
      "native_address" : "0x314802bd4",
      "native_offset" : "0x00000"
   }
,
  {
      "is_managed" : "false",
      "native_address" : "0x189b16584",
      "native_offset" : "0x00000"
   }
,
  {
      "is_managed" : "false",
      "native_address" : "0x3148383e0",
      "native_offset" : "0x00000"
   }
,
  {
      "is_managed" : "false",
      "native_address" : "0x31482f760",
      "native_offset" : "0x00000"
   }
,
  {
      "is_managed" : "false",
      "native_address" : "0x3148f94f4",
      "native_offset" : "0x00000"
   }
,
  {
      "is_managed" : "false",
      "native_address" : "0x3148f93a0",
      "native_offset" : "0x00000"
   }
,
  {
      "is_managed" : "false",
      "native_address" : "0x314978cb0",
      "native_offset" : "0x00000"
   }
,
  {
      "is_managed" : "false",
      "native_address" : "0x314978c38",
      "native_offset" : "0x00000"
   }
,
  {
      "is_managed" : "false",
      "native_address" : "0x189ae5f94",
      "native_offset" : "0x00000"
   }
,
  {
      "is_managed" : "false",
      "native_address" : "0x189ae0d34",
      "native_offset" : "0x00000"
   }

  ]
 },
 {
    "is_managed" : false,
    "offset_free_hash" : "0x0",
    "offset_rich_hash" : "0x0",
    "crashed" : false,
    "native_thread_id" : "0x333913000",
    "thread_info_addr" : "0x12f668800",
    "thread_name" : "Thread Pool Worker",
    "ctx" : {
      "IP" : "0x189aa4d88",
      "SP" : "0x333912db0",
      "BP" : "0x333912e50"
  },
    "unmanaged_frames" : [
  {
      "is_managed" : "false",
      "native_address" : "0x3147c1c58",
      "native_offset" : "0x00000"
   }
,
  {
      "is_managed" : "false",
      "native_address" : "0x3148f8788",
      "native_offset" : "0x00000"
   }
,
  {
      "is_managed" : "false",
      "native_address" : "0x3148f8ae4",
      "native_offset" : "0x00000"
   }
,
  {
      "is_managed" : "false",
      "native_address" : "0x3148f88ac",
      "native_offset" : "0x00000"
   }
,
  {
      "is_managed" : "false",
      "native_address" : "0x314802bd4",
      "native_offset" : "0x00000"
   }
,
  {
      "is_managed" : "false",
      "native_address" : "0x189b16584",
      "native_offset" : "0x00000"
   }
,
  {
      "is_managed" : "false",
      "native_address" : "0x314850c70",
      "native_offset" : "0x00000"
   }
,
  {
      "is_managed" : "false",
      "native_address" : "0x3148f94f4",
      "native_offset" : "0x00000"
   }
,
  {
      "is_managed" : "false",
      "native_address" : "0x3148f93a0",
      "native_offset" : "0x00000"
   }
,
  {
      "is_managed" : "false",
      "native_address" : "0x314978cb0",
      "native_offset" : "0x00000"
   }
,
  {
      "is_managed" : "false",
      "native_address" : "0x314978c38",
      "native_offset" : "0x00000"
   }
,
  {
      "is_managed" : "false",
      "native_address" : "0x189ae5f94",
      "native_offset" : "0x00000"
   }
,
  {
      "is_managed" : "false",
      "native_address" : "0x189ae0d34",
      "native_offset" : "0x00000"
   }

  ]
 },
 {
    "is_managed" : true,
    "offset_free_hash" : "0xfb24c9124",
    "offset_rich_hash" : "0xfb24c92ad",
    "crashed" : false,
    "native_thread_id" : "0x3961f3000",
    "thread_info_addr" : "0x144eb3200",
    "thread_name" : "tid_3dd2f",
    "ctx" : {
      "IP" : "0x189aa85ec",
      "SP" : "0x3961f2520",
      "BP" : "0x3961f25b0"
  },
    "managed_frames" : [
  {
      "is_managed" : "false",
      "native_address" : "unregistered"
   }
,
  {
      "is_managed" : "true",
      "guid" : "1FE4B731-1082-47D3-A7E5-7FAD336611B9",
      "token" : "0x00000",
      "native_offset" : "0x0",
      "filename" : "mscorlib.dll",
      "sizeofimage" : "0x470000",
      "timestamp" : "0x8e492f34",
      "il_offset" : "0xffffffff"
   }
,
  {
      "is_managed" : "true",
      "guid" : "1FE4B731-1082-47D3-A7E5-7FAD336611B9",
      "token" : "0x6001f5d",
      "native_offset" : "0x0",
      "filename" : "mscorlib.dll",
      "sizeofimage" : "0x470000",
      "timestamp" : "0x8e492f34",
      "il_offset" : "0x0002f"
   }
,
  {
      "is_managed" : "true",
      "guid" : "1FE4B731-1082-47D3-A7E5-7FAD336611B9",
      "token" : "0x6001f50",
      "native_offset" : "0x0",
      "filename" : "mscorlib.dll",
      "sizeofimage" : "0x470000",
      "timestamp" : "0x8e492f34",
      "il_offset" : "0x0000e"
   }
,
  {
      "is_managed" : "true",
      "guid" : "1FE4B731-1082-47D3-A7E5-7FAD336611B9",
      "token" : "0x6001f52",
      "native_offset" : "0x0",
      "filename" : "mscorlib.dll",
      "sizeofimage" : "0x470000",
      "timestamp" : "0x8e492f34",
      "il_offset" : "0x00000"
   }
,
  {
      "is_managed" : "true",
      "guid" : "8733359C-E0F4-484D-9455-5ABD8C9D784F",
      "token" : "0x60058b0",
      "native_offset" : "0x0",
      "filename" : "unityplastic.dll",
      "sizeofimage" : "0x4d4000",
      "timestamp" : "0x62793241",
      "il_offset" : "0x00030"
   }
,
  {
      "is_managed" : "true",
      "guid" : "1FE4B731-1082-47D3-A7E5-7FAD336611B9",
      "token" : "0x6001f7d",
      "native_offset" : "0x0",
      "filename" : "mscorlib.dll",
      "sizeofimage" : "0x470000",
      "timestamp" : "0x8e492f34",
      "il_offset" : "0x00014"
   }
,
  {
      "is_managed" : "true",
      "guid" : "1FE4B731-1082-47D3-A7E5-7FAD336611B9",
      "token" : "0x6001f25",
      "native_offset" : "0x0",
      "filename" : "mscorlib.dll",
      "sizeofimage" : "0x470000",
      "timestamp" : "0x8e492f34",
      "il_offset" : "0x00071"
   }
,
  {
      "is_managed" : "true",
      "guid" : "1FE4B731-1082-47D3-A7E5-7FAD336611B9",
      "token" : "0x6001f23",
      "native_offset" : "0x0",
      "filename" : "mscorlib.dll",
      "sizeofimage" : "0x470000",
      "timestamp" : "0x8e492f34",
      "il_offset" : "0x00000"
   }
,
  {
      "is_managed" : "true",
      "guid" : "1FE4B731-1082-47D3-A7E5-7FAD336611B9",
      "token" : "0x6001f22",
      "native_offset" : "0x0",
      "filename" : "mscorlib.dll",
      "sizeofimage" : "0x470000",
      "timestamp" : "0x8e492f34",
      "il_offset" : "0x0002b"
   }
,
  {
      "is_managed" : "true",
      "guid" : "1FE4B731-1082-47D3-A7E5-7FAD336611B9",
      "token" : "0x6001f7f",
      "native_offset" : "0x0",
      "filename" : "mscorlib.dll",
      "sizeofimage" : "0x470000",
      "timestamp" : "0x8e492f34",
      "il_offset" : "0x00008"
   }
,
  {
      "is_managed" : "true",
      "guid" : "1FE4B731-1082-47D3-A7E5-7FAD336611B9",
      "token" : "0x00000",
      "native_offset" : "0x0",
      "filename" : "mscorlib.dll",
      "sizeofimage" : "0x470000",
      "timestamp" : "0x8e492f34",
      "il_offset" : "0x00065"
   }

  ],
  "unmanaged_frames" : [
 {
    "is_managed" : "false",
    "native_address" : "0x3147c1c58",
    "native_offset" : "0x00000"
  }
,
 {
    "is_managed" : "false",
    "native_address" : "0x3148f8788",
    "native_offset" : "0x00000"
  }
,
 {
    "is_managed" : "false",
    "native_address" : "0x3148f8ae4",
    "native_offset" : "0x00000"
  }
,
 {
    "is_managed" : "false",
    "native_address" : "0x3148f88ac",
    "native_offset" : "0x00000"
  }
,
 {
    "is_managed" : "false",
    "native_address" : "0x314802bd4",
    "native_offset" : "0x00000"
  }
,
 {
    "is_managed" : "false",
    "native_address" : "0x189b16584",
    "native_offset" : "0x00000"
  }
,
 {
    "is_managed" : "false",
    "native_address" : "0x189ae6588",
    "native_offset" : "0x00000"
  }
,
 {
    "is_managed" : "false",
    "native_address" : "0x314947e08",
    "native_offset" : "0x00000"
  }
,
 {
    "is_managed" : "false",
    "native_address" : "0x3149044b0",
    "native_offset" : "0x00000"
  }
,
 {
    "is_managed" : "false",
    "native_address" : "0x3149042e4",
    "native_offset" : "0x00000"
  }
,
 {
    "is_managed" : "false",
    "native_address" : "0x3149335d8",
    "native_offset" : "0x00000"
  }
,
 {
    "is_managed" : "false",
    "native_address" : "0x31489cc8c",
    "native_offset" : "0x00000"
  }
,
 {
    "is_managed" : "true",
    "guid" : "1FE4B731-1082-47D3-A7E5-7FAD336611B9",
    "token" : "0x00000",
    "native_offset" : "0x0",
    "filename" : "mscorlib.dll",
    "sizeofimage" : "0x470000",
    "timestamp" : "0x8e492f34",
    "il_offset" : "0x00000"
  }
,
 {
    "is_managed" : "true",
    "guid" : "1FE4B731-1082-47D3-A7E5-7FAD336611B9",
    "token" : "0x6001f5d",
    "native_offset" : "0x0",
    "filename" : "mscorlib.dll",
    "sizeofimage" : "0x470000",
    "timestamp" : "0x8e492f34",
    "il_offset" : "0x00000"
  }
,
 {
    "is_managed" : "true",
    "guid" : "1FE4B731-1082-47D3-A7E5-7FAD336611B9",
    "token" : "0x6001f50",
    "native_offset" : "0x0",
    "filename" : "mscorlib.dll",
    "sizeofimage" : "0x470000",
    "timestamp" : "0x8e492f34",
    "il_offset" : "0x00000"
  }
,
 {
    "is_managed" : "true",
    "guid" : "1FE4B731-1082-47D3-A7E5-7FAD336611B9",
    "token" : "0x6001f52",
    "native_offset" : "0x0",
    "filename" : "mscorlib.dll",
    "sizeofimage" : "0x470000",
    "timestamp" : "0x8e492f34",
    "il_offset" : "0x00000"
  }
,
 {
    "is_managed" : "true",
    "guid" : "8733359C-E0F4-484D-9455-5ABD8C9D784F",
    "token" : "0x60058b0",
    "native_offset" : "0x0",
    "filename" : "unityplastic.dll",
    "sizeofimage" : "0x4d4000",
    "timestamp" : "0x62793241",
    "il_offset" : "0x00000"
  }
,
 {
    "is_managed" : "true",
    "guid" : "1FE4B731-1082-47D3-A7E5-7FAD336611B9",
    "token" : "0x6001f7d",
    "native_offset" : "0x0",
    "filename" : "mscorlib.dll",
    "sizeofimage" : "0x470000",
    "timestamp" : "0x8e492f34",
    "il_offset" : "0x00000"
  }
,
 {
    "is_managed" : "true",
    "guid" : "1FE4B731-1082-47D3-A7E5-7FAD336611B9",
    "token" : "0x6001f25",
    "native_offset" : "0x0",
    "filename" : "mscorlib.dll",
    "sizeofimage" : "0x470000",
    "timestamp" : "0x8e492f34",
    "il_offset" : "0x00000"
  }
,
 {
    "is_managed" : "true",
    "guid" : "1FE4B731-1082-47D3-A7E5-7FAD336611B9",
    "token" : "0x6001f23",
    "native_offset" : "0x0",
    "filename" : "mscorlib.dll",
    "sizeofimage" : "0x470000",
    "timestamp" : "0x8e492f34",
    "il_offset" : "0x00000"
  }
,
 {
    "is_managed" : "true",
    "guid" : "1FE4B731-1082-47D3-A7E5-7FAD336611B9",
    "token" : "0x6001f22",
    "native_offset" : "0x0",
    "filename" : "mscorlib.dll",
    "sizeofimage" : "0x470000",
    "timestamp" : "0x8e492f34",
    "il_offset" : "0x00000"
  }
,
 {
    "is_managed" : "true",
    "guid" : "1FE4B731-1082-47D3-A7E5-7FAD336611B9",
    "token" : "0x6001f7f",
    "native_offset" : "0x0",
    "filename" : "mscorlib.dll",
    "sizeofimage" : "0x470000",
    "timestamp" : "0x8e492f34",
    "il_offset" : "0x00000"
  }
,
 {
    "is_managed" : "true",
    "guid" : "1FE4B731-1082-47D3-A7E5-7FAD336611B9",
    "token" : "0x00000",
    "native_offset" : "0x0",
    "filename" : "mscorlib.dll",
    "sizeofimage" : "0x470000",
    "timestamp" : "0x8e492f34",
    "il_offset" : "0x00000"
  }
,
 {
    "is_managed" : "false",
    "native_address" : "0x31475190c",
    "native_offset" : "0x00000"
  }
,
 {
    "is_managed" : "false",
    "native_address" : "0x3148d76a8",
    "native_offset" : "0x00000"
  }
,
 {
    "is_managed" : "false",
    "native_address" : "0x3148d92a4",
    "native_offset" : "0x00000"
  }
,
 {
    "is_managed" : "false",
    "native_address" : "0x3148f95e8",
    "native_offset" : "0x00000"
  }
,
 {
    "is_managed" : "false",
    "native_address" : "0x3148f93a0",
    "native_offset" : "0x00000"
  }
,
 {
    "is_managed" : "false",
    "native_address" : "0x314978cb0",
    "native_offset" : "0x00000"
  }
,
 {
    "is_managed" : "false",
    "native_address" : "0x314978c38",
    "native_offset" : "0x00000"
  }
,
 {
    "is_managed" : "false",
    "native_address" : "0x189ae5f94",
    "native_offset" : "0x00000"
  }
,
 {
    "is_managed" : "false",
    "native_address" : "0x189ae0d34",
    "native_offset" : "0x00000"
  }

 ]
},
{
  "is_managed" : false,
  "offset_free_hash" : "0x0",
  "offset_rich_hash" : "0x0",
  "crashed" : true,
  "native_thread_id" : "0x1f1934f40",
  "thread_info_addr" : "0x12c96fc00",
  "thread_name" : "tid_103",
  "ctx" : {
    "IP" : "0x102b8a02c",
    "SP" : "0x16dc9cb90",
    "BP" : "0x16dc9cba0"
 },
  "unmanaged_frames" : [
 {
    "is_managed" : "false",
    "native_address" : "0x3147c1c58",
    "native_offset" : "0x00000"
  }
,
 {
    "is_managed" : "false",
    "native_address" : "0x3148f8788",
    "native_offset" : "0x00000"
  }
,
 {
    "is_managed" : "false",
    "native_address" : "0x3148f8ae4",
    "native_offset" : "0x00000"
  }
,
 {
    "is_managed" : "false",
    "native_address" : "0x3148f90d4",
    "native_offset" : "0x00000"
  }
,
 {
    "is_managed" : "false",
    "native_address" : "0x314803a20",
    "native_offset" : "0x00000"
  }
,
 {
    "is_managed" : "false",
    "native_address" : "0x3147c5d5c",
    "native_offset" : "0x00000"
  }
,
 {
    "is_managed" : "false",
    "native_address" : "0x31474e64c",
    "native_offset" : "0x00000"
  }
,
 {
    "is_managed" : "false",
    "native_address" : "0x189b16584",
    "native_offset" : "0x00000"
  }
,
 {
    "is_managed" : "false",
    "native_address" : "0x102b8a02c",
    "native_offset" : "0x00000"
  }
,
 {
    "is_managed" : "false",
    "native_address" : "0x1039ab80c",
    "native_offset" : "0x00000"
  }
,
 {
    "is_managed" : "false",
    "native_address" : "0x1037cd278",
    "native_offset" : "0x00000"
  }
,
 {
    "is_managed" : "false",
    "native_address" : "0x103e2f858",
    "native_offset" : "0x00000"
  }
,
 {
    "is_managed" : "false",
    "native_address" : "0x103e30e6c",
    "native_offset" : "0x00000"
  }
,
 {
    "is_managed" : "false",
    "native_address" : "0x103dcca74",
    "native_offset" : "0x00000"
  }
,
 {
    "is_managed" : "false",
    "native_address" : "0x102a6c88c",
    "native_offset" : "0x00000"
  }
,
 {
    "is_managed" : "false",
    "native_address" : "0x102a6bcf0",
    "native_offset" : "0x00000"
  }
,
 {
    "is_managed" : "false",
    "native_address" : "0x102a6b52c",
    "native_offset" : "0x00000"
  }
,
 {
    "is_managed" : "false",
    "native_address" : "0x102a6a9d4",
    "native_offset" : "0x00000"
  }
,
 {
    "is_managed" : "false",
    "native_address" : "0x102a6d838",
    "native_offset" : "0x00000"
  }
,
 {
    "is_managed" : "false",
    "native_address" : "0x102a6e304",
    "native_offset" : "0x00000"
  }
,
 {
    "is_managed" : "false",
    "native_address" : "0x10399f97c",
    "native_offset" : "0x00000"
  }
,
 {
    "is_managed" : "false",
    "native_address" : "0x103c43364",
    "native_offset" : "0x00000"
  }
,
 {
    "is_managed" : "false",
    "native_address" : "0x103c3b104",
    "native_offset" : "0x00000"
  }
,
 {
    "is_managed" : "false",
    "native_address" : "0x103c3939c",
    "native_offset" : "0x00000"
  }
,
 {
    "is_managed" : "false",
    "native_address" : "0x1049c90f0",
    "native_offset" : "0x00000"
  }
,
 {
    "is_managed" : "false",
    "native_address" : "0x18ad31288",
    "native_offset" : "0x00000"
  }
,
 {
    "is_managed" : "false",
    "native_address" : "0x189be15b8",
    "native_offset" : "0x00000"
  }
,
 {
    "is_managed" : "false",
    "native_address" : "0x189be125c",
    "native_offset" : "0x00000"
  }
,
 {
    "is_managed" : "false",
    "native_address" : "0x189be0d94",
    "native_offset" : "0x00000"
  }
,
 {
    "is_managed" : "false",
    "native_address" : "0x189bc41cc",
    "native_offset" : "0x00000"
  }
,
 {
    "is_managed" : "false",
    "native_address" : "0x189bc3434",
    "native_offset" : "0x00000"
  }
,
 {
    "is_managed" : "false",
    "native_address" : "0x19436d19c",
    "native_offset" : "0x00000"
  }
,
 {
    "is_managed" : "false",
    "native_address" : "0x19436cfd8",
    "native_offset" : "0x00000"
  }
,
 {
    "is_managed" : "false",
    "native_address" : "0x19436cd30",
    "native_offset" : "0x00000"
  }
,
 {
    "is_managed" : "false",
    "native_address" : "0x18d422cc8",
    "native_offset" : "0x00000"
  }
,
 {
    "is_managed" : "false",
    "native_address" : "0x18dc194d0",
    "native_offset" : "0x00000"
  }
,
 {
    "is_managed" : "false",
    "native_address" : "0x18d415ffc",
    "native_offset" : "0x00000"
  }
,
 {
    "is_managed" : "false",
    "native_address" : "0x18d3ed240",
    "native_offset" : "0x00000"
  }
,
 {
    "is_managed" : "false",
    "native_address" : "0x1049c63c8",
    "native_offset" : "0x00000"
  }
,
 {
    "is_managed" : "false",
    "native_address" : "0x1049c6700",
    "native_offset" : "0x00000"
  }
,
 {
    "is_managed" : "false",
    "native_address" : "0x18975b154",
    "native_offset" : "0x00000"
  }

 ]
},
{
  "is_managed" : false,
  "offset_free_hash" : "0x0",
  "offset_rich_hash" : "0x0",
  "crashed" : false,
  "native_thread_id" : "0x33721f000",
  "thread_info_addr" : "0x12c355800",
  "thread_name" : "Thread Pool Worker",
  "ctx" : {
    "IP" : "0x189aa4d88",
    "SP" : "0x33721edb0",
    "BP" : "0x33721ee50"
 },
  "unmanaged_frames" : [
 {
    "is_managed" : "false",
    "native_address" : "0x3147c1c58",
    "native_offset" : "0x00000"
  }
,
 {
    "is_managed" : "false",
    "native_address" : "0x3148f8788",
    "native_offset" : "0x00000"
  }
,
 {
    "is_managed" : "false",
    "native_address" : "0x3148f8ae4",
    "native_offset" : "0x00000"
  }
,
 {
    "is_managed" : "false",
    "native_address" : "0x3148f88ac",
    "native_offset" : "0x00000"
  }
,
 {
    "is_managed" : "false",
    "native_address" : "0x314802bd4",
    "native_offset" : "0x00000"
  }
,
 {
    "is_managed" : "false",
    "native_address" : "0x189b16584",
    "native_offset" : "0x00000"
  }
,
 {
    "is_managed" : "false",
    "native_address" : "0x314850c70",
    "native_offset" : "0x00000"
  }
,
 {
    "is_managed" : "false",
    "native_address" : "0x3148f94f4",
    "native_offset" : "0x00000"
  }
,
 {
    "is_managed" : "false",
    "native_address" : "0x3148f93a0",
    "native_offset" : "0x00000"
  }
,
 {
    "is_managed" : "false",
    "native_address" : "0x314978cb0",
    "native_offset" : "0x00000"
  }
,
 {
    "is_managed" : "false",
    "native_address" : "0x314978c38",
    "native_offset" : "0x00000"
  }
,
 {
    "is_managed" : "false",
    "native_address" : "0x189ae5f94",
    "native_offset" : "0x00000"
  }
,
 {
    "is_managed" : "false",
    "native_address" : "0x189ae0d34",
    "native_offset" : "0x00000"
  }

 ]
},
{
  "is_managed" : false,
  "offset_free_hash" : "0x0",
  "offset_rich_hash" : "0x0",
  "crashed" : false,
  "native_thread_id" : "0x331c0f000",
  "thread_info_addr" : "0x12f6cc400",
  "thread_name" : "tid_25607",
  "ctx" : {
    "IP" : "0x189aa85ec",
    "SP" : "0x331c0ec20",
    "BP" : "0x331c0ecb0"
 },
  "unmanaged_frames" : [
 {
    "is_managed" : "false",
    "native_address" : "0x3147c1c58",
    "native_offset" : "0x00000"
  }
,
 {
    "is_managed" : "false",
    "native_address" : "0x3148f8788",
    "native_offset" : "0x00000"
  }
,
 {
    "is_managed" : "false",
    "native_address" : "0x3148f8ae4",
    "native_offset" : "0x00000"
  }
,
 {
    "is_managed" : "false",
    "native_address" : "0x3148f88ac",
    "native_offset" : "0x00000"
  }
,
 {
    "is_managed" : "false",
    "native_address" : "0x314802bd4",
    "native_offset" : "0x00000"
  }
,
 {
    "is_managed" : "false",
    "native_address" : "0x189b16584",
    "native_offset" : "0x00000"
  }
,
 {
    "is_managed" : "false",
    "native_address" : "0x189ae6588",
    "native_offset" : "0x00000"
  }
,
 {
    "is_managed" : "false",
    "native_address" : "0x314947e08",
    "native_offset" : "0x00000"
  }
,
 {
    "is_managed" : "false",
    "native_address" : "0x314951ae4",
    "native_offset" : "0x00000"
  }
,
 {
    "is_managed" : "false",
    "native_address" : "0x314850478",
    "native_offset" : "0x00000"
  }
,
 {
    "is_managed" : "false",
    "native_address" : "0x3148f94f4",
    "native_offset" : "0x00000"
  }
,
 {
    "is_managed" : "false",
    "native_address" : "0x3148f93a0",
    "native_offset" : "0x00000"
  }
,
 {
    "is_managed" : "false",
    "native_address" : "0x314978cb0",
    "native_offset" : "0x00000"
  }
,
 {
    "is_managed" : "false",
    "native_address" : "0x314978c38",
    "native_offset" : "0x00000"
  }
,
 {
    "is_managed" : "false",
    "native_address" : "0x189ae5f94",
    "native_offset" : "0x00000"
  }
,
 {
    "is_managed" : "false",
    "native_address" : "0x189ae0d34",
    "native_offset" : "0x00000"
  }

 ]
},
{
  "is_managed" : false,
  "offset_free_hash" : "0x0",
  "offset_rich_hash" : "0x0",
  "crashed" : false,
  "native_thread_id" : "0x331e1b000",
  "thread_info_addr" : "0x317720e00",
  "thread_name" : "Thread Pool Worker",
  "ctx" : {
    "IP" : "0x189aa4d88",
    "SP" : "0x331e1adb0",
    "BP" : "0x331e1ae50"
 },
  "unmanaged_frames" : [
 {
    "is_managed" : "false",
    "native_address" : "0x3147c1c58",
    "native_offset" : "0x00000"
  }
,
 {
    "is_managed" : "false",
    "native_address" : "0x3148f8788",
    "native_offset" : "0x00000"
  }
,
 {
    "is_managed" : "false",
    "native_address" : "0x3148f8ae4",
    "native_offset" : "0x00000"
  }
,
 {
    "is_managed" : "false",
    "native_address" : "0x3148f88ac",
    "native_offset" : "0x00000"
  }
,
 {
    "is_managed" : "false",
    "native_address" : "0x314802bd4",
    "native_offset" : "0x00000"
  }
,
 {
    "is_managed" : "false",
    "native_address" : "0x189b16584",
    "native_offset" : "0x00000"
  }
,
 {
    "is_managed" : "false",
    "native_address" : "0x314850c70",
    "native_offset" : "0x00000"
  }
,
 {
    "is_managed" : "false",
    "native_address" : "0x3148f94f4",
    "native_offset" : "0x00000"
  }
,
 {
    "is_managed" : "false",
    "native_address" : "0x3148f93a0",
    "native_offset" : "0x00000"
  }
,
 {
    "is_managed" : "false",
    "native_address" : "0x314978cb0",
    "native_offset" : "0x00000"
  }
,
 {
    "is_managed" : "false",
    "native_address" : "0x314978c38",
    "native_offset" : "0x00000"
  }
,
 {
    "is_managed" : "false",
    "native_address" : "0x189ae5f94",
    "native_offset" : "0x00000"
  }
,
 {
    "is_managed" : "false",
    "native_address" : "0x189ae0d34",
    "native_offset" : "0x00000"
  }

 ]
},
{
  "is_managed" : false,
  "offset_free_hash" : "0x0",
  "offset_rich_hash" : "0x0",
  "crashed" : false,
  "native_thread_id" : "0x314feb000",
  "thread_info_addr" : "0x12d8d5a00",
  "thread_name" : "Finalizer",
  "ctx" : {
    "IP" : "0x189aa4d70",
    "SP" : "0x314feadd0",
    "BP" : "0x314feae50"
 },
  "unmanaged_frames" : [
 {
    "is_managed" : "false",
    "native_address" : "0x3147c1c58",
    "native_offset" : "0x00000"
  }
,
 {
    "is_managed" : "false",
    "native_address" : "0x3148f8788",
    "native_offset" : "0x00000"
  }
,
 {
    "is_managed" : "false",
    "native_address" : "0x3148f8ae4",
    "native_offset" : "0x00000"
  }
,
 {
    "is_managed" : "false",
    "native_address" : "0x3148f88ac",
    "native_offset" : "0x00000"
  }
,
 {
    "is_managed" : "false",
    "native_address" : "0x314802bd4",
    "native_offset" : "0x00000"
  }
,
 {
    "is_managed" : "false",
    "native_address" : "0x189b16584",
    "native_offset" : "0x00000"
  }
,
 {
    "is_managed" : "false",
    "native_address" : "0x314932294",
    "native_offset" : "0x00000"
  }
,
 {
    "is_managed" : "false",
    "native_address" : "0x3148f94f4",
    "native_offset" : "0x00000"
  }
,
 {
    "is_managed" : "false",
    "native_address" : "0x3148f93a0",
    "native_offset" : "0x00000"
  }
,
 {
    "is_managed" : "false",
    "native_address" : "0x314978cb0",
    "native_offset" : "0x00000"
  }
,
 {
    "is_managed" : "false",
    "native_address" : "0x314978c38",
    "native_offset" : "0x00000"
  }
,
 {
    "is_managed" : "false",
    "native_address" : "0x189ae5f94",
    "native_offset" : "0x00000"
  }
,
 {
    "is_managed" : "false",
    "native_address" : "0x189ae0d34",
    "native_offset" : "0x00000"
  }

 ]
},
{
  "is_managed" : false,
  "offset_free_hash" : "0x0",
  "offset_rich_hash" : "0x0",
  "crashed" : false,
  "native_thread_id" : "0x332bb7000",
  "thread_info_addr" : "0x12f665c00",
  "thread_name" : "Thread Pool Worker",
  "ctx" : {
    "IP" : "0x189aa4d88",
    "SP" : "0x332bb6db0",
    "BP" : "0x332bb6e50"
 },
  "unmanaged_frames" : [
 {
    "is_managed" : "false",
    "native_address" : "0x3147c1c58",
    "native_offset" : "0x00000"
  }
,
 {
    "is_managed" : "false",
    "native_address" : "0x3148f8788",
    "native_offset" : "0x00000"
  }
,
 {
    "is_managed" : "false",
    "native_address" : "0x3148f8ae4",
    "native_offset" : "0x00000"
  }
,
 {
    "is_managed" : "false",
    "native_address" : "0x3148f88ac",
    "native_offset" : "0x00000"
  }
,
 {
    "is_managed" : "false",
    "native_address" : "0x314802bd4",
    "native_offset" : "0x00000"
  }
,
 {
    "is_managed" : "false",
    "native_address" : "0x189b16584",
    "native_offset" : "0x00000"
  }
,
 {
    "is_managed" : "false",
    "native_address" : "0x314850c70",
    "native_offset" : "0x00000"
  }
,
 {
    "is_managed" : "false",
    "native_address" : "0x3148f94f4",
    "native_offset" : "0x00000"
  }
,
 {
    "is_managed" : "false",
    "native_address" : "0x3148f93a0",
    "native_offset" : "0x00000"
  }
,
 {
    "is_managed" : "false",
    "native_address" : "0x314978cb0",
    "native_offset" : "0x00000"
  }
,
 {
    "is_managed" : "false",
    "native_address" : "0x314978c38",
    "native_offset" : "0x00000"
  }
,
 {
    "is_managed" : "false",
    "native_address" : "0x189ae5f94",
    "native_offset" : "0x00000"
  }
,
 {
    "is_managed" : "false",
    "native_address" : "0x189ae0d34",
    "native_offset" : "0x00000"
  }

 ]
},
{
  "is_managed" : false,
  "offset_free_hash" : "0x0",
  "offset_rich_hash" : "0x0",
  "crashed" : false,
  "native_thread_id" : "0x327507000",
  "thread_info_addr" : "0x144867a00",
  "thread_name" : "tid_2d31b",
  "ctx" : {
    "IP" : "0x189aa4d70",
    "SP" : "0x327506d50",
    "BP" : "0x327506d60"
 },
  "unmanaged_frames" : [
 {
    "is_managed" : "false",
    "native_address" : "0x3147c1c58",
    "native_offset" : "0x00000"
  }
,
 {
    "is_managed" : "false",
    "native_address" : "0x3148f8788",
    "native_offset" : "0x00000"
  }
,
 {
    "is_managed" : "false",
    "native_address" : "0x3148f8ae4",
    "native_offset" : "0x00000"
  }
,
 {
    "is_managed" : "false",
    "native_address" : "0x3148f88ac",
    "native_offset" : "0x00000"
  }
,
 {
    "is_managed" : "false",
    "native_address" : "0x314802bd4",
    "native_offset" : "0x00000"
  }
,
 {
    "is_managed" : "false",
    "native_address" : "0x189b16584",
    "native_offset" : "0x00000"
  }
,
 {
    "is_managed" : "false",
    "native_address" : "0x189935984",
    "native_offset" : "0x00000"
  }
,
 {
    "is_managed" : "false",
    "native_address" : "0x189936034",
    "native_offset" : "0x00000"
  }
,
 {
    "is_managed" : "false",
    "native_address" : "0x104b69f30",
    "native_offset" : "0x00000"
  }
,
 {
    "is_managed" : "false",
    "native_address" : "0x1026c931c",
    "native_offset" : "0x00000"
  }
,
 {
    "is_managed" : "false",
    "native_address" : "0x102a6df58",
    "native_offset" : "0x00000"
  }
,
 {
    "is_managed" : "false",
    "native_address" : "0x102a6daf4",
    "native_offset" : "0x00000"
  }
,
 {
    "is_managed" : "false",
    "native_address" : "0x102a6da64",
    "native_offset" : "0x00000"
  }
,
 {
    "is_managed" : "false",
    "native_address" : "0x102bf0810",
    "native_offset" : "0x00000"
  }
,
 {
    "is_managed" : "false",
    "native_address" : "0x189ae5f94",
    "native_offset" : "0x00000"
  }
,
 {
    "is_managed" : "false",
    "native_address" : "0x189ae0d34",
    "native_offset" : "0x00000"
  }

 ]
}
]
}